[
  { "slug": "ahmedabad", "name": "Ahmedabad", "state": "gujarat", "marketTier": "tier2", "center": [23.0225, 72.5714], "radiusKm": 45, "aliases": ["ahmedabad", "amdavad"] },
  { "slug": "surat", "name": "Surat", "state": "gujarat", "marketTier": "tier2", "center": [21.1702, 72.8311], "radiusKm": 38, "aliases": ["surat"] },
  { "slug": "vadodara", "name": "Vadodara", "state": "gujarat", "marketTier": "tier2", "center": [22.3072, 73.1812], "radiusKm": 32, "aliases": ["vadodara", "baroda"] },
  { "slug": "rajkot", "name": "Rajkot", "state": "gujarat", "marketTier": "tier3", "center": [22.3039, 70.8022], "radiusKm": 30, "aliases": ["rajkot"] },
  { "slug": "indore", "name": "Indore", "state": "madhya-pradesh", "marketTier": "tier2", "center": [22.7196, 75.8577], "radiusKm": 38, "aliases": ["indore"] },
  { "slug": "bhopal", "name": "Bhopal", "state": "madhya-pradesh", "marketTier": "tier2", "center": [23.2599, 77.4126], "radiusKm": 36, "aliases": ["bhopal"] },
  { "slug": "jabalpur", "name": "Jabalpur", "state": "madhya-pradesh", "marketTier": "tier3", "center": [23.1815, 79.9864], "radiusKm": 28, "aliases": ["jabalpur"] },
  { "slug": "gwalior", "name": "Gwalior", "state": "madhya-pradesh", "marketTier": "tier3", "center": [26.2183, 78.1828], "radiusKm": 28, "aliases": ["gwalior"] },
  { "slug": "jaipur", "name": "Jaipur", "state": "rajasthan", "marketTier": "tier2", "center": [26.9124, 75.7873], "radiusKm": 45, "aliases": ["jaipur"] },
  { "slug": "jodhpur", "name": "Jodhpur", "state": "rajasthan", "marketTier": "tier3", "center": [26.2389, 73.0243], "radiusKm": 30, "aliases": ["jodhpur"] },
  { "slug": "udaipur", "name": "Udaipur", "state": "rajasthan", "marketTier": "tier3", "center": [24.5854, 73.7125], "radiusKm": 28, "aliases": ["udaipur"] },
  { "slug": "kota", "name": "Kota", "state": "rajasthan", "marketTier": "tier3", "center": [25.2138, 75.8648], "radiusKm": 28, "aliases": ["kota"] },
  { "slug": "lucknow", "name": "Lucknow", "state": "uttar-pradesh", "marketTier": "tier2", "center": [26.8467, 80.9462], "radiusKm": 42, "aliases": ["lucknow"] },
  { "slug": "kanpur", "name": "Kanpur", "state": "uttar-pradesh", "marketTier": "tier2", "center": [26.4499, 80.3319], "radiusKm": 36, "aliases": ["kanpur", "cawnpore"] },
  { "slug": "varanasi", "name": "Varanasi", "state": "uttar-pradesh", "marketTier": "tier3", "center": [25.3176, 82.9739], "radiusKm": 28, "aliases": ["varanasi", "banaras", "kashi"] },
  { "slug": "prayagraj", "name": "Prayagraj", "state": "uttar-pradesh", "marketTier": "tier3", "center": [25.4358, 81.8463], "radiusKm": 28, "aliases": ["prayagraj", "allahabad"] },
  { "slug": "meerut", "name": "Meerut", "state": "uttar-pradesh", "marketTier": "tier3", "center": [28.9845, 77.7064], "radiusKm": 30, "aliases": ["meerut"] },
  { "slug": "agra", "name": "Agra", "state": "uttar-pradesh", "marketTier": "tier3", "center": [27.1767, 78.0081], "radiusKm": 28, "aliases": ["agra"] },
  { "slug": "coimbatore", "name": "Coimbatore", "state": "tamil-nadu", "marketTier": "tier2", "center": [11.0168, 76.9558], "radiusKm": 38, "aliases": ["coimbatore", "kovai"] },
  { "slug": "madurai", "name": "Madurai", "state": "tamil-nadu", "marketTier": "tier3", "center": [9.9252, 78.1198], "radiusKm": 28, "aliases": ["madurai"] },
  { "slug": "tiruchirappalli", "name": "Tiruchirappalli", "state": "tamil-nadu", "marketTier": "tier3", "center": [10.7905, 78.7047], "radiusKm": 28, "aliases": ["tiruchirappalli", "trichy"] },
  { "slug": "salem", "name": "Salem", "state": "tamil-nadu", "marketTier": "tier3", "center": [11.6643, 78.1460], "radiusKm": 26, "aliases": ["salem"] },
  { "slug": "tiruppur", "name": "Tiruppur", "state": "tamil-nadu", "marketTier": "tier3", "center": [11.1085, 77.3411], "radiusKm": 26, "aliases": ["tiruppur"] },
  { "slug": "kochi", "name": "Kochi", "state": "kerala", "marketTier": "tier2", "center": [9.9312, 76.2673], "radiusKm": 36, "aliases": ["kochi", "cochin", "ernakulam"] },
  { "slug": "thiruvananthapuram", "name": "Thiruvananthapuram", "state": "kerala", "marketTier": "tier2", "center": [8.5241, 76.9366], "radiusKm": 34, "aliases": ["thiruvananthapuram", "trivandrum"] },
  { "slug": "kozhikode", "name": "Kozhikode", "state": "kerala", "marketTier": "tier3", "center": [11.2588, 75.7804], "radiusKm": 28, "aliases": ["kozhikode", "calicut"] },
  { "slug": "thrissur", "name": "Thrissur", "state": "kerala", "marketTier": "tier3", "center": [10.5276, 76.2144], "radiusKm": 26, "aliases": ["thrissur", "trichur"] },
  { "slug": "mysuru", "name": "Mysuru", "state": "karnataka", "marketTier": "tier2", "center": [12.2958, 76.6394], "radiusKm": 34, "aliases": ["mysuru", "mysore"] },
  { "slug": "mangaluru", "name": "Mangaluru", "state": "karnataka", "marketTier": "tier3", "center": [12.9141, 74.8560], "radiusKm": 28, "aliases": ["mangaluru", "mangalore"] },
  { "slug": "hubballi-dharwad", "name": "Hubballi-Dharwad", "state": "karnataka", "marketTier": "tier3", "center": [15.3647, 75.1240], "radiusKm": 32, "aliases": ["hubballi", "hubli", "dharwad", "hubballi dharwad"] },
  { "slug": "belagavi", "name": "Belagavi", "state": "karnataka", "marketTier": "tier3", "center": [15.8497, 74.4977], "radiusKm": 26, "aliases": ["belagavi", "belgaum"] },
  { "slug": "nagpur", "name": "Nagpur", "state": "maharashtra", "marketTier": "tier2", "center": [21.1458, 79.0882], "radiusKm": 40, "aliases": ["nagpur"] },
  { "slug": "nashik", "name": "Nashik", "state": "maharashtra", "marketTier": "tier2", "center": [19.9975, 73.7898], "radiusKm": 34, "aliases": ["nashik", "nasik"] },
  { "slug": "chhatrapati-sambhajinagar", "name": "Chhatrapati Sambhajinagar", "state": "maharashtra", "marketTier": "tier3", "center": [19.8762, 75.3433], "radiusKm": 28, "aliases": ["chhatrapati sambhajinagar", "aurangabad"] },
  { "slug": "kolhapur", "name": "Kolhapur", "state": "maharashtra", "marketTier": "tier3", "center": [16.7050, 74.2433], "radiusKm": 26, "aliases": ["kolhapur"] },
  { "slug": "amravati", "name": "Amravati", "state": "maharashtra", "marketTier": "tier3", "center": [20.9374, 77.7796], "radiusKm": 26, "aliases": ["amravati"] },
  { "slug": "bhubaneswar-cuttack", "name": "Bhubaneswar-Cuttack", "state": "odisha", "marketTier": "tier2", "center": [20.3730, 85.8190], "radiusKm": 42, "aliases": ["bhubaneswar", "cuttack", "bhubaneswar cuttack"] },
  { "slug": "rourkela", "name": "Rourkela", "state": "odisha", "marketTier": "tier3", "center": [22.2604, 84.8536], "radiusKm": 26, "aliases": ["rourkela"] },
  { "slug": "raipur", "name": "Raipur", "state": "chhattisgarh", "marketTier": "tier2", "center": [21.2514, 81.6296], "radiusKm": 34, "aliases": ["raipur"] },
  { "slug": "bhilai-durg", "name": "Bhilai-Durg", "state": "chhattisgarh", "marketTier": "tier3", "center": [21.1938, 81.3509], "radiusKm": 30, "aliases": ["bhilai", "durg", "bhilai durg"] },
  { "slug": "ranchi", "name": "Ranchi", "state": "jharkhand", "marketTier": "tier2", "center": [23.3441, 85.3096], "radiusKm": 32, "aliases": ["ranchi"] },
  { "slug": "jamshedpur", "name": "Jamshedpur", "state": "jharkhand", "marketTier": "tier3", "center": [22.8046, 86.2029], "radiusKm": 28, "aliases": ["jamshedpur", "tatanagar"] },
  { "slug": "patna", "name": "Patna", "state": "bihar", "marketTier": "tier2", "center": [25.5941, 85.1376], "radiusKm": 36, "aliases": ["patna"] },
  { "slug": "gaya", "name": "Gaya", "state": "bihar", "marketTier": "tier3", "center": [24.7914, 85.0002], "radiusKm": 26, "aliases": ["gaya"] },
  { "slug": "guwahati", "name": "Guwahati", "state": "assam", "marketTier": "tier2", "center": [26.1445, 91.7362], "radiusKm": 36, "aliases": ["guwahati", "gauhati"] },
  { "slug": "silchar", "name": "Silchar", "state": "assam", "marketTier": "tier3", "center": [24.8333, 92.7789], "radiusKm": 24, "aliases": ["silchar"] },
  { "slug": "chandigarh-tricity", "name": "Chandigarh Tricity", "state": "chandigarh-punjab-haryana", "marketTier": "tier2", "center": [30.7333, 76.7794], "radiusKm": 38, "aliases": ["chandigarh", "mohali", "panchkula", "zirakpur", "tricity"] },
  { "slug": "ludhiana", "name": "Ludhiana", "state": "punjab", "marketTier": "tier2", "center": [30.9010, 75.8573], "radiusKm": 30, "aliases": ["ludhiana"] },
  { "slug": "amritsar", "name": "Amritsar", "state": "punjab", "marketTier": "tier3", "center": [31.6340, 74.8723], "radiusKm": 28, "aliases": ["amritsar"] },
  { "slug": "dehradun", "name": "Dehradun", "state": "uttarakhand", "marketTier": "tier3", "center": [30.3165, 78.0322], "radiusKm": 30, "aliases": ["dehradun"] },
  { "slug": "haridwar-rishikesh", "name": "Haridwar-Rishikesh", "state": "uttarakhand", "marketTier": "tier3", "center": [29.9457, 78.1642], "radiusKm": 30, "aliases": ["haridwar", "rishikesh", "haridwar rishikesh"] },
  { "slug": "tirupati", "name": "Tirupati", "state": "andhra-pradesh", "marketTier": "tier3", "center": [13.6288, 79.4192], "radiusKm": 28, "aliases": ["tirupati"] },
  { "slug": "nellore", "name": "Nellore", "state": "andhra-pradesh", "marketTier": "tier3", "center": [14.4426, 79.9865], "radiusKm": 28, "aliases": ["nellore"] },
  { "slug": "kurnool", "name": "Kurnool", "state": "andhra-pradesh", "marketTier": "tier3", "center": [15.8281, 78.0373], "radiusKm": 28, "aliases": ["kurnool"] },
  { "slug": "rajahmundry", "name": "Rajahmundry", "state": "andhra-pradesh", "marketTier": "tier3", "center": [17.0005, 81.8040], "radiusKm": 28, "aliases": ["rajahmundry", "rajamahendravaram"] },
  { "slug": "kakinada", "name": "Kakinada", "state": "andhra-pradesh", "marketTier": "tier3", "center": [16.9891, 82.2475], "radiusKm": 26, "aliases": ["kakinada"] },
  { "slug": "guntur", "name": "Guntur", "state": "andhra-pradesh", "marketTier": "tier3", "center": [16.3067, 80.4365], "radiusKm": 30, "aliases": ["guntur"] },
  { "slug": "warangal", "name": "Warangal", "state": "telangana", "marketTier": "tier3", "center": [17.9689, 79.5941], "radiusKm": 32, "aliases": ["warangal", "hanumakonda"] },
  { "slug": "karimnagar", "name": "Karimnagar", "state": "telangana", "marketTier": "tier3", "center": [18.4386, 79.1288], "radiusKm": 28, "aliases": ["karimnagar"] },
  { "slug": "nizamabad", "name": "Nizamabad", "state": "telangana", "marketTier": "tier3", "center": [18.6725, 78.0941], "radiusKm": 28, "aliases": ["nizamabad"] }
]
